llama_server/__init__.py
llama_server/server.py
llama_server/prompts/alpaca.txt
llama_server/prompts/chat-with-bob.txt
llama_server/prompts/dan.txt
llama_server/prompts/reason-act.txt
llama_server-0.2.2.dist-info/LICENSE
llama_server-0.2.2.dist-info/METADATA
llama_server-0.2.2.dist-info/WHEEL
llama_server-0.2.2.dist-info/entry_points.txt
llama_server-0.2.2.dist-info/top_level.txt
llama_server-0.2.2.dist-info/RECORD
