Metadata-Version: 2.1
Name: llama-server
Version: 0.2.2
Summary: LLaMA Server combines the power of LLaMA C++ with the beauty of Chatbot UI.
Home-page: https://github.com/nuance1979/llama-server
Author: Yi Su
Author-email: nuance@gmail.com
License: MIT
Keywords: llama llama.cpp chatbot-ui chatbot
Classifier: Development Status :: 4 - Beta
Classifier: Intended Audience :: Science/Research
Classifier: Topic :: Scientific/Engineering :: Artificial Intelligence
Classifier: Topic :: Software Development :: Libraries :: Python Modules
Classifier: License :: OSI Approved :: MIT License
Classifier: Programming Language :: Python :: 3.8
Classifier: Programming Language :: Python :: 3.9
Classifier: Programming Language :: Python :: 3.10
Requires-Python: >=3.8
License-File: LICENSE
Requires-Dist: pyllamacpp
Requires-Dist: fastapi
Requires-Dist: uvicorn[standard]
Requires-Dist: sse-starlette
Requires-Dist: click
Provides-Extra: dev
Requires-Dist: httpx ; extra == 'dev'
Requires-Dist: pre-commit ; extra == 'dev'
Requires-Dist: pytest ; extra == 'dev'
Requires-Dist: pytest-cov ; extra == 'dev'
Requires-Dist: pytest-xdist ; extra == 'dev'
Requires-Dist: numpy ; extra == 'dev'
